.gitignore
LICENSE
README.md
setup.cfg
setup.py
docs/lfp.md
examples/circular_disrtibution.py
examples/filatrate_lfp.py
examples/mean_spike_rate.py
examples/phase_ampls_coupliing.py
examples/phase_phase_coupling.py
examples/remove_artifacts.py
examples/ripples_detection.py
neurotool/__init__.py
neurotool/circstat.py
neurotool/lfp.py
neurotool/spatial.py
neurotool/spikes.py
neurotool.egg-info/PKG-INFO
neurotool.egg-info/SOURCES.txt
neurotool.egg-info/dependency_links.txt
neurotool.egg-info/requires.txt
neurotool.egg-info/top_level.txt