Metadata-Version: 2.1
Name: neurotool
Version: 0.0.2
Summary: LFP and spikes processing
Home-page: https://github.com/ivanmysin/NeuroTools
Author: Ivan Mysin, Sergey Dubrovin, Sergey Skorokhod, Artem Vasilev
Author-email: imysin@mail.ru
License: UNKNOWN
Project-URL: Documentation, https://github.com/ivanmysin/NeuroTools/tree/master/docs
Keywords: brain rhythms neuron spike lfp place cells hippocampus
Platform: UNKNOWN
Classifier: Programming Language :: Python :: 3.10
Classifier: License :: OSI Approved :: MIT License
Classifier: Operating System :: OS Independent
Requires-Python: >=3.7
License-File: LICENSE
